jvirtualenv/__init__.py
jvirtualenv/__main__.py
jvirtualenv/support/__init__.py
jvirtualenv/support/minghu6_support.py
jvirtualenv/template/__init__.py
jvirtualenv/template/activate_template.py
jvirtualenv/template/activate_template_bat.py
jvirtualenv/template/deactivate_template_bat.py
jvirtualenv-0.1.0.dist-info/DESCRIPTION.rst
jvirtualenv-0.1.0.dist-info/METADATA
jvirtualenv-0.1.0.dist-info/RECORD
jvirtualenv-0.1.0.dist-info/WHEEL
jvirtualenv-0.1.0.dist-info/entry_points.txt
jvirtualenv-0.1.0.dist-info/metadata.json
jvirtualenv-0.1.0.dist-info/top_level.txt
