Metadata-Version: 2.0
Name: jvirtualenv
Version: 0.1.0
Summary: micro virtualenv for Java
Home-page: https://github.com/minghu6/jvirtualenv
Author: minghu6
Author-email: a19678zy@163.com
License: BSD License
Platform: UNKNOWN
Classifier: Development Status :: 4 - Beta
Classifier: Intended Audience :: Developers
Classifier: License :: OSI Approved :: BSD License
Classifier: Operating System :: OS Independent
Classifier: Programming Language :: Python :: 3
Classifier: Programming Language :: Python :: Implementation :: CPython
Requires-Dist: docopt
Requires-Dist: color-print (==0.0.2)
Requires-Dist: sh
